{
  "id": "king-of-tower-dice",
  "title": "King of Tower Dice",
  "description": "Adds a custom six-sided KoT die for Dice So Nice with configurable labels and colors.",
  "version": "0.1.1",
  "type": "module",
  "url": "https://github.com/jstapels/king-of-tower-dice",
  "manifest": "https://github.com/jstapels/king-of-tower-dice/releases/latest/download/module.json",
  "download": "https://github.com/jstapels/king-of-tower-dice/releases/download/v0.1.1/king-of-tower-dice.zip",
  "readme": "https://github.com/jstapels/king-of-tower-dice/blob/main/README.md",
  "bugs": "https://github.com/jstapels/king-of-tower-dice/issues",
  "media": [],
  "authors": [
    {
      "name": "J. Stapels"
    }
  ],
  "compatibility": {
    "minimum": "14",
    "verified": "14.360"
  },
  "relationships": {
    "requires": [
      {
        "id": "dice-so-nice",
        "type": "module",
        "compatibility": {
          "minimum": "6.1.0",
          "verified": "6.1.0"
        }
      }
    ]
  },
  "esmodules": [
    "scripts/kot-dice.js"
  ],
  "readme": "README.md"
}
